doxycore.py
doxybuild-0.1.1_alpha.data/scripts/doxybuild.py
doxybuild-0.1.1_alpha.dist-info/DESCRIPTION.rst
doxybuild-0.1.1_alpha.dist-info/METADATA
doxybuild-0.1.1_alpha.dist-info/metadata.json
doxybuild-0.1.1_alpha.dist-info/RECORD
doxybuild-0.1.1_alpha.dist-info/top_level.txt
doxybuild-0.1.1_alpha.dist-info/WHEEL
